<?xml version="1.0"?>
<ModelDocumentManifest xmlns:xsi="http://www.w3.org/2001/XMLSchema-instance" xmlns:xsd="http://www.w3.org/2001/XMLSchema">
  <Documents>
    <Document FullPath="C:\Apps\github.com\autocompletebox\SuburbsSearch\SuburbsSearch.DesktopClient\Properties\Client.lsml" Checksum="6089641FC972591B4DA34429A23E97CFF09DE496511789C592FA8AC019D04392" />
    <Document FullPath="C:\Apps\github.com\autocompletebox\SuburbsSearch\SuburbsSearch.DesktopClient\Properties\Proxies.lsml" Checksum="54CA5BEC13A3BD28559D772A6BDA92356615C3B497DF97DCCF820DBACA527A41" />
    <Document FullPath="C:\Apps\github.com\autocompletebox\SuburbsSearch\SuburbsSearch.DesktopClient\Screens\ContactsScreen.lsml" Checksum="846DE19E8339576F74F428E4ED7B86CCD0597463818BB76ADB58534F48C20EE4" />
    <Document FullPath="C:\Apps\github.com\autocompletebox\SuburbsSearch\SuburbsSearch.DesktopClient\Screens\EditableStatesGrid.lsml" Checksum="08247CABD67DD363F43065D4B8E7E691B9617102B6FCBEDB8CDC9930C640CEBC" />
    <Document FullPath="C:\Apps\github.com\autocompletebox\SuburbsSearch\SuburbsSearch.DesktopClient\Screens\MatterScreen.lsml" Checksum="1E4BDED28011CFF8857A71460EAA20189688DC40FF11623D5C662BC5586F71BE" />
    <Document FullPath="C:\Apps\github.com\autocompletebox\SuburbsSearch\SuburbsSearch.DesktopClient\Screens\SearchMatterScreen.lsml" Checksum="178B92F071CA356DC1DDC3E778CF794253B1A280868AD141C770F893A08F43BC" />
    <Document FullPath="C:\Apps\github.com\autocompletebox\SuburbsSearch\SuburbsSearch.DesktopClient\Screens\SuburbScreen.lsml" Checksum="F650739390112746ADDD3F740F77FD6212AEE940A8F19AF8FCFE18DE49BFC59F" />
  </Documents>
</ModelDocumentManifest>